__main__/__init__.py
eptc/__init__.py
eptc/eptc.py
eptc-0.0.3.dist-info/LICENSE
eptc-0.0.3.dist-info/METADATA
eptc-0.0.3.dist-info/WHEEL
eptc-0.0.3.dist-info/top_level.txt
eptc-0.0.3.dist-info/RECORD
